pyppmd/__init__.py
pyppmd/py.typed
pyppmd/cffi/_cffi_ppmd.pypy39-pp73-x86_64-linux-gnu.so
pyppmd/cffi/cffi_ppmd.py
pyppmd/c/c_ppmd.py
pyppmd-1.1.1.dist-info/top_level.txt
pyppmd-1.1.1.dist-info/RECORD
pyppmd-1.1.1.dist-info/LICENSE
pyppmd-1.1.1.dist-info/METADATA
pyppmd-1.1.1.dist-info/WHEEL
