Metadata-Version: 2.1
Name: pyppmd
Version: 1.1.1
Summary: PPMd compression/decompression library
Author-email: Hiroshi Miura <miurahr@linux.com>
License: LGPL-2.1-or-later
Project-URL: Source, https://codeberg.org/miurahr/pyppmd
Project-URL: Homepage, https://pyppmd.readthedocs.io/
Project-URL: Documentation, https://pyppmd.readthedocs.io/en/stable/
Project-URL: Bug Tracker, https://codeberg.org/miurahr/pyppmd/issues
Project-URL: Changelog, https://pyppmd.readthedocs.io/en/latest/changelog.html
Classifier: Development Status :: 5 - Production/Stable
Classifier: License :: OSI Approved :: GNU Lesser General Public License v2 or later (LGPLv2+)
Classifier: Operating System :: MacOS :: MacOS X
Classifier: Operating System :: Microsoft :: Windows
Classifier: Operating System :: POSIX
Classifier: Operating System :: POSIX :: Linux
Classifier: Programming Language :: Python
Classifier: Programming Language :: Python :: 3
Classifier: Programming Language :: Python :: 3.9
Classifier: Programming Language :: Python :: 3.10
Classifier: Programming Language :: Python :: 3.11
Classifier: Programming Language :: Python :: 3.12
Classifier: Programming Language :: Python :: 3.13
Classifier: Programming Language :: Python :: 3 :: Only
Classifier: Programming Language :: Python :: Implementation :: CPython
Classifier: Programming Language :: Python :: Implementation :: PyPy
Classifier: Topic :: Software Development :: Libraries :: Python Modules
Requires-Python: >=3.9
License-File: LICENSE
Provides-Extra: test
Requires-Dist: pytest>=6.0; extra == "test"
Requires-Dist: pytest-benchmark; extra == "test"
Requires-Dist: pytest-cov; extra == "test"
Requires-Dist: pytest-timeout; extra == "test"
Requires-Dist: hypothesis; extra == "test"
Requires-Dist: coverage[toml]>=5.2; extra == "test"
Provides-Extra: check
Requires-Dist: mypy>=1.10.0; extra == "check"
Requires-Dist: check-manifest; extra == "check"
Requires-Dist: flake8; extra == "check"
Requires-Dist: flake8-isort; extra == "check"
Requires-Dist: flake8-black; extra == "check"
Requires-Dist: readme-renderer; extra == "check"
Requires-Dist: pygments; extra == "check"
Provides-Extra: docs
Requires-Dist: sphinx; extra == "docs"
Requires-Dist: sphinx_rtd_theme; extra == "docs"
Provides-Extra: fuzzer
Requires-Dist: atheris; extra == "fuzzer"
Requires-Dist: hypothesis; extra == "fuzzer"
